ERlib/Funciones.py
ERlib/__init__.py
ERlib-1.dist-info/METADATA
ERlib-1.dist-info/WHEEL
ERlib-1.dist-info/top_level.txt
ERlib-1.dist-info/RECORD
