Metadata-Version: 2.1
Name: ERlib
Version: 1
Summary: Librería para imprimir tablas
Home-page: https://github.com/ERwiin21MP
Author: Erwin Martínez Pérez
Author-email: erwinmartinezperez@gmail.com
License: GPLv3
Platform: UNKNOWN
